Metadata-Version: 2.1
Name: antee-c-header-macro-generator
Version: 1.0.0
Summary: C header macro name generator
Home-page: https://github.com/zhangyiant/c_header_macro_generator
Author: Yi Zhang
Author-email: zhangyiant@hotmail.com
License: UNKNOWN
Platform: UNKNOWN
Classifier: Programming Language :: Python :: 3
Classifier: License :: OSI Approved :: MIT License
Classifier: Operating System :: OS Independent
Requires-Python: >=3.7
